SpaDecon/DEC.py
SpaDecon/ItClust.py
SpaDecon/SAE.py
SpaDecon/SpaDecon.py
SpaDecon/__init__.py
SpaDecon/calculate_adj.py
SpaDecon/preprocessing.py
SpaDecon/utils.py
SpaDecon-1.1.2.dist-info/LICENSE
SpaDecon-1.1.2.dist-info/METADATA
SpaDecon-1.1.2.dist-info/WHEEL
SpaDecon-1.1.2.dist-info/top_level.txt
SpaDecon-1.1.2.dist-info/RECORD
