Metadata-Version: 2.1
Name: SpaDecon
Version: 1.1.2
Summary: SpaDecon: cell-type deconvolution in spatial transcriptomics with semi-supervised learning
Home-page: https://github.com/kylepcoleman87/SpaDecon
Author: Kyle Coleman
Author-email: kylecole@pennmedicine.upenn.edu
Classifier: Programming Language :: Python :: 3
Classifier: License :: OSI Approved :: MIT License
Classifier: Operating System :: OS Independent
Requires-Python: >=3.6
License-File: LICENSE
Requires-Dist: keras (==2.2.4)
Requires-Dist: pandas (==1.2.4)
Requires-Dist: numpy (==1.20.1)
Requires-Dist: scipy (==1.6.2)
Requires-Dist: scanpy (==1.7.0)
Requires-Dist: anndata (==0.7.6)
Requires-Dist: sklearn
Requires-Dist: tensorflow (==1.14.0)
